healthcheck_python/__init__.py
healthcheck_python/health.py
healthcheck_python/release.py
healthcheck_python/server.py
healthcheck_python-1.2.2.dist-info/LICENSE
healthcheck_python-1.2.2.dist-info/METADATA
healthcheck_python-1.2.2.dist-info/WHEEL
healthcheck_python-1.2.2.dist-info/entry_points.txt
healthcheck_python-1.2.2.dist-info/RECORD
