Metadata-Version: 2.1
Name: healthcheck-python
Version: 1.2.2
Summary: Health Check API for multiprocessing python apps
Home-page: https://github.com/cagdasbas/healthcheck-python
License: Apache-2.0
Author: Cagdas Bas
Author-email: cagdasbs@gmail.com
Maintainer: Cagdas Bas
Maintainer-email: cagdasbs@gmail.com
Requires-Python: >=3.8
Classifier: Development Status :: 5 - Production/Stable
Classifier: Intended Audience :: Developers
Classifier: License :: OSI Approved :: Apache Software License
Classifier: Natural Language :: English
Classifier: Operating System :: OS Independent
Classifier: Programming Language :: Python :: 3
Classifier: Programming Language :: Python :: 3.8
Classifier: Programming Language :: Python :: 3.9
Classifier: Programming Language :: Python :: 3.10
Classifier: Programming Language :: Python :: 3.11
Project-URL: Repository, https://github.com/cagdasbas/healthcheck-python
